LICENSE
README.md
wtf.py
wtf_config.py
wtf_preview.sh
wtf_launcher-0.1.1.dist-info/METADATA
wtf_launcher-0.1.1.dist-info/WHEEL
wtf_launcher-0.1.1.dist-info/entry_points.txt
wtf_launcher-0.1.1.dist-info/licenses/LICENSE
wtf_launcher-0.1.1.dist-info/RECORD
