Metadata-Version: 2.4
Name: wtf-launcher
Version: 0.1.1
Summary: What The F*** Can I Run? - Fast command launcher
Project-URL: Homepage, https://github.com/adriangalilea/wtf
Project-URL: Repository, https://github.com/adriangalilea/wtf
Project-URL: Issues, https://github.com/adriangalilea/wtf/issues
Author-email: Adrian Galilea <adriangalilea@gmail.com>
License: MIT
License-File: LICENSE
Keywords: cli,command,fzf,launcher,terminal
Classifier: Development Status :: 3 - Alpha
Classifier: Environment :: Console
Classifier: Intended Audience :: Developers
Classifier: License :: OSI Approved :: MIT License
Classifier: Operating System :: MacOS
Classifier: Operating System :: POSIX :: Linux
Classifier: Programming Language :: Python :: 3
Classifier: Programming Language :: Python :: 3.12
Classifier: Programming Language :: Python :: 3.13
Classifier: Topic :: System :: Shells
Classifier: Topic :: Utilities
Requires-Python: >=3.12
Requires-Dist: pydantic>=2.0
